hidio/__init__.py
hidio/client/__init__.py
hidio/schema/__init__.py
hidio/schema/common.capnp
hidio/schema/devicefunction.capnp
hidio/schema/hidio.capnp
hidio/schema/hidiowatcher.capnp
hidio/schema/hostmacro.capnp
hidio/schema/usbkeyboard.capnp
hidio-0.1.0b1.dist-info/WHEEL
hidio-0.1.0b1.dist-info/METADATA
hidio-0.1.0b1.dist-info/RECORD
