Metadata-Version: 2.1
Name: hidio
Version: 0.1.0b1
Summary: HID-IO Python Library
Home-page: https://github.com/kiibohd/kll
License: UNKNOWN
Author: Jacob Alexander
Author-email: haata@kiibohd.com
Requires-Python: >=3.7
Classifier: Topic :: Software Development :: Libraries
Classifier: Intended Audience :: Developers
Classifier: Programming Language :: Python :: 3
Requires-Dist: cython>=0.29.12
Requires-Dist: pycapnp==0.6.4
